{
    "pipeline_type": "stream",
    "name": "SAROP21-PBPS138_proc",
    "bsread_address": "",
    "bsread_channels": [
        "SAROP21-CVME-PBPS2:Lnk9Ch1-DATA-SUM",
        "SAROP21-CVME-PBPS2:Lnk9Ch2-DATA-SUM",
        "SAROP21-CVME-PBPS2:Lnk9Ch3-DATA-SUM",
        "SAROP21-CVME-PBPS2:Lnk9Ch4-DATA-SUM"
    ],
    "mode": "PUB",
    "function": "pbps.py",
    "reload": true,
    "no_client_timeout": 0,
    "port": "9009",
    "up": "SAROP21-CVME-PBPS2:Lnk9Ch4-DATA-SUM",
    "down": "SAROP21-CVME-PBPS2:Lnk9Ch3-DATA-SUM",
    "right": "SAROP21-CVME-PBPS2:Lnk9Ch1-DATA-SUM",
    "left": "SAROP21-CVME-PBPS2:Lnk9Ch2-DATA-SUM",
    "up_calib": 0.08713157252045031,
    "down_calib": 0.07438197630437833,
    "left_calib": 0.14413433421172023,
    "right_calib": 0.19525084217966876,
    "horiz_calib": 2.8959614484256484,
    "vert_calib": -4.341028771625084,
    "uJ_calib": 605.9512700123181,
    "threshold": 0,
    "queue_length": 1000,
    "xpos_all_x_pvname": "SAROP21-PBPS138:XPOS-ALL-HIST-X",
    "xpos_all_y_pvname": "SAROP21-PBPS138:XPOS-ALL-HIST-Y",
    "xpos_all_m_pvname": "SAROP21-PBPS138:XPOS-ALL-HIST-M",
    "xpos_all_w_pvname": "SAROP21-PBPS138:XPOS-ALL-HIST-W",
    "ypos_all_x_pvname": "SAROP21-PBPS138:YPOS-ALL-HIST-X",
    "ypos_all_y_pvname": "SAROP21-PBPS138:YPOS-ALL-HIST-Y",
    "ypos_all_m_pvname": "SAROP21-PBPS138:YPOS-ALL-HIST-M",
    "ypos_all_w_pvname": "SAROP21-PBPS138:YPOS-ALL-HIST-W",
    "xpos_evn_x_pvname": "SAROP21-PBPS138:XPOS-EVN-HIST-X",
    "xpos_evn_y_pvname": "SAROP21-PBPS138:XPOS-EVN-HIST-Y",
    "xpos_evn_m_pvname": "SAROP21-PBPS138:XPOS-EVN-HIST-M",
    "xpos_evn_w_pvname": "SAROP21-PBPS138:XPOS-EVN-HIST-W",
    "ypos_evn_x_pvname": "SAROP21-PBPS138:YPOS-EVN-HIST-X",
    "ypos_evn_y_pvname": "SAROP21-PBPS138:YPOS-EVN-HIST-Y",
    "ypos_evn_m_pvname": "SAROP21-PBPS138:YPOS-EVN-HIST-M",
    "ypos_evn_w_pvname": "SAROP21-PBPS138:YPOS-EVN-HIST-W",
    "xpos_odd_x_pvname": "SAROP21-PBPS138:XPOS-ODD-HIST-X",
    "xpos_odd_y_pvname": "SAROP21-PBPS138:XPOS-ODD-HIST-Y",
    "xpos_odd_m_pvname": "SAROP21-PBPS138:XPOS-ODD-HIST-M",
    "xpos_odd_w_pvname": "SAROP21-PBPS138:XPOS-ODD-HIST-W",
    "ypos_odd_x_pvname": "SAROP21-PBPS138:YPOS-ODD-HIST-X",
    "ypos_odd_y_pvname": "SAROP21-PBPS138:YPOS-ODD-HIST-Y",
    "ypos_odd_m_pvname": "SAROP21-PBPS138:YPOS-ODD-HIST-M",
    "ypos_odd_w_pvname": "SAROP21-PBPS138:YPOS-ODD-HIST-W",
    "xpos_dif_m_pvname": "SAROP21-PBPS138:XPOS-DIF-HIST-M",
    "xpos_dif_w_pvname": "SAROP21-PBPS138:XPOS-DIF-HIST-W",
    "ypos_dif_m_pvname": "SAROP21-PBPS138:YPOS-DIF-HIST-M",
    "ypos_dif_w_pvname": "SAROP21-PBPS138:YPOS-DIF-HIST-W"
}